isosurfaces/__init__.py
isosurfaces/cell.py
isosurfaces/isoline.py
isosurfaces/isosurface.py
isosurfaces/point.py
isosurfaces/py.typed
isosurfaces-0.1.1.dist-info/LICENSE
isosurfaces-0.1.1.dist-info/METADATA
isosurfaces-0.1.1.dist-info/WHEEL
isosurfaces-0.1.1.dist-info/top_level.txt
isosurfaces-0.1.1.dist-info/RECORD
