Metadata-Version: 2.1
Name: isosurfaces
Version: 0.1.1
Summary: Construct isolines/isosurfaces over a 2D/3D scalar field defined by a function (not a uniform grid)
Home-page: https://github.com/jared-hughes/isosurfaces
Author: Jared Hughes
Author-email: jahughes.dev@gmail.com
License: MIT
Classifier: License :: OSI Approved :: MIT License
Classifier: Programming Language :: Python :: 3
Classifier: Programming Language :: Python :: 3.8
Classifier: Programming Language :: Python :: 3.9
Classifier: Programming Language :: Python :: 3.10
Classifier: Programming Language :: Python :: 3.11
Classifier: Programming Language :: Python :: 3.12
Classifier: Typing :: Typed
Requires-Python: >=3.8
License-File: LICENSE
Requires-Dist: numpy
